knowlexp/__init__.py
knowlexp/knlp.py
knowlexp-0.0.1.dist-info/LICENCE.txt
knowlexp-0.0.1.dist-info/METADATA
knowlexp-0.0.1.dist-info/WHEEL
knowlexp-0.0.1.dist-info/top_level.txt
knowlexp-0.0.1.dist-info/RECORD
